mashup_main/__init__.py
mashup_main/main_102117021.py
mashup_main/merge_audio.py
mashup_main/yt_funcs.py
Mashup_102117021-0.0.1.dist-info/METADATA
Mashup_102117021-0.0.1.dist-info/WHEEL
Mashup_102117021-0.0.1.dist-info/top_level.txt
Mashup_102117021-0.0.1.dist-info/RECORD
