Metadata-Version: 2.1
Name: Mashup-102117021
Version: 0.0.1
Summary: Mashup of audio files from youtube videos.
Author: intrinsicvardhan (Aaditya Vardhan)
Author-email: intrinsicvardhan@gmail.com
Keywords: mashup,youtube,web-scraping,audio-processing,audio-merging,audio-cutting,audio-mixing,audio-editing,audio-manipulation,audio-concatenation
Classifier: Development Status :: 1 - Planning
Classifier: Intended Audience :: Developers
Classifier: Programming Language :: Python :: 3
Classifier: Operating System :: Unix
Classifier: Operating System :: MacOS :: MacOS X
Classifier: Operating System :: Microsoft :: Windows
Requires-Dist: selenium
Requires-Dist: pydub
Requires-Dist: pytube
